README.md
hdb/__init__.py
hdb/cli.py
hdb/cluster.py
hdb/config.py
hdb/init.py
hdb/job.py
hdb/util.py
hdb/cli_installer/cli-installer.sql
hdb/commands/cleanroom-request.sql
hdb/commands/create-cleanroom.sql
hdb/commands/create-dataset.sql
hdb/commands/new-data-connection.sql
hdb/resource/config.yaml
habu_databricks_cli-1.3.2.dist-info/METADATA
habu_databricks_cli-1.3.2.dist-info/WHEEL
habu_databricks_cli-1.3.2.dist-info/entry_points.txt
habu_databricks_cli-1.3.2.dist-info/top_level.txt
habu_databricks_cli-1.3.2.dist-info/RECORD
