Metadata-Version: 2.1
Name: habu-databricks-cli
Version: 1.3.2
Summary: Habu Databricks Cli
Home-page: https://www.habu.com
Author: Habu Engineering
Author-email: engineering@habu.com
Requires-Python: >=3.6
Requires-Dist: requests ~=2.28.2
Requires-Dist: click ~=7.1.2
Requires-Dist: tinynetrc ~=1.3.1
Requires-Dist: ruamel.yaml ~=0.17.21
